EpinanoPredict.py
EpinanoPredict-0.1.2.dist-info/LICENSE
EpinanoPredict-0.1.2.dist-info/METADATA
EpinanoPredict-0.1.2.dist-info/WHEEL
EpinanoPredict-0.1.2.dist-info/top_level.txt
EpinanoPredict-0.1.2.dist-info/RECORD
